{
  "pensamentos": [
    {
      "id": 7,
      "conteudo": "Eu te amo",
      "autoria": "Elaine",
      "modelo": "modelo3",
      "favorito": false
    },
    {
      "conteudo": "Renato ama a mamãe Elaine e o Juca",
      "autoria": "filho renato",
      "modelo": "modelo2",
      "favorito": true,
      "id": 10
    },
    {
      "conteudo": "Eu não sei mãe",
      "autoria": "filho renato",
      "modelo": "modelo3",
      "favorito": false,
      "id": 17
    },
    {
      "conteudo": "que saco, mãe",
      "autoria": "filho renato",
      "modelo": "modelo2",
      "favorito": false,
      "id": 18
    },
    {
      "conteudo": "fica quieto, que eu quero estudar",
      "autoria": "mãe elaine",
      "modelo": "modelo2",
      "favorito": false,
      "id": 19
    },
    {
      "conteudo": "Eu não sei de nada",
      "autoria": "filho renato",
      "modelo": "modelo1",
      "favorito": false,
      "id": 20
    },
    {
      "conteudo": "au au au au",
      "autoria": "filho juca",
      "modelo": "modelo2",
      "favorito": false,
      "id": 21
    },
    {
      "conteudo": "Hoje quero ir ao shopping em Santo André",
      "autoria": "filho renato",
      "modelo": "modelo3",
      "favorito": false,
      "id": 22
    },
    {
      "conteudo": "hoje passeamos com Ana e Mariana no shopping ABC",
      "autoria": "renato e elaine",
      "modelo": "modelo2",
      "favorito": false,
      "id": 23
    }
  ]
}